[
  {
    "id": 1,
    "name": "Une expo a enregistrer comme ca pour tester",
    "shortDescription": "Exposition à Château des Ducs de Bretagne numéro 1",
    "longDescription": "Exposition à Château des Ducs de Bretagne description longue, en fait pas si longue mais suffisamment longue pour être considérée comme longue",
    "startDate": "2024-10-12T13:29:06.092Z",
    "endDate": "2025-03-14T14:29:06.092Z",
    "site": {
      "id": 1,
      "name": "Château des Ducs de Bretagne"
    },
    "exhibitedItems": [
      {
        "item": {
          "id": 1,
          "name": "Couronne du Duc François II",
          "site": {
            "id": 1,
            "name": "Château des Ducs de Bretagne"
          }
        }
      },
      {
        "item": {
          "id": 2,
          "name": "Épée de Gilles de Rais",
          "site": {
            "id": 1,
            "name": "Château des Ducs de Bretagne"
          }
        }
      },
      {
        "item": {
          "id": 4,
          "name": "Tableau de la Révolution Française",
          "site": {
            "id": 1,
            "name": "Château des Ducs de Bretagne"
          }
        }
      },
      {
        "item": {
          "id": 5,
          "name": "Manteau du Duc de Bretagne",
          "site": {
            "id": 1,
            "name": "Château des Ducs de Bretagne"
          }
        }
      },
      {
        "item": {
          "id": 3,
          "name": "Statue de la Liberté",
          "site": {
            "id": 1,
            "name": "Château des Ducs de Bretagne"
          }
        }
      }
    ]
  },
  {
    "id": 2,
    "name": "Exposition à Château des Ducs de Bretagne numéro 2",
    "shortDescription": "Exposition à Château des Ducs de Bretagne numéro 2",
    "longDescription": "Exposition à Château des Ducs de Bretagne description longue, en fait pas si longue mais suffisamment longue pour être considérée comme longue",
    "startDate": "1970-01-01T00:00:00.015Z",
    "endDate": "1970-06-22T00:00:00.015Z",
    "site": {
      "id": 1,
      "name": "Château des Ducs de Bretagne"
    },
    "exhibitedItems": [
      {
        "item": {
          "id": 3,
          "name": "Statue de la Liberté",
          "site": {
            "id": 1,
            "name": "Château des Ducs de Bretagne"
          }
        }
      },
      {
        "item": {
          "id": 5,
          "name": "Manteau du Duc de Bretagne",
          "site": {
            "id": 1,
            "name": "Château des Ducs de Bretagne"
          }
        }
      },
      {
        "item": {
          "id": 4,
          "name": "Tableau de la Révolution Française",
          "site": {
            "id": 1,
            "name": "Château des Ducs de Bretagne"
          }
        }
      },
      {
        "item": {
          "id": 2,
          "name": "Épée de Gilles de Rais",
          "site": {
            "id": 1,
            "name": "Château des Ducs de Bretagne"
          }
        }
      },
      {
        "item": {
          "id": 1,
          "name": "Couronne du Duc François II",
          "site": {
            "id": 1,
            "name": "Château des Ducs de Bretagne"
          }
        }
      }
    ]
  },
  {
    "id": 3,
    "name": "Exposition à Château des Ducs de Bretagne numéro 3",
    "shortDescription": "Exposition à Château des Ducs de Bretagne numéro 3",
    "longDescription": "Exposition à Château des Ducs de Bretagne description longue, en fait pas si longue mais suffisamment longue pour être considérée comme longue",
    "startDate": "1970-01-01T00:00:00.023Z",
    "endDate": "1970-03-03T00:00:00.023Z",
    "site": {
      "id": 1,
      "name": "Château des Ducs de Bretagne"
    },
    "exhibitedItems": [
      {
        "item": {
          "id": 2,
          "name": "Épée de Gilles de Rais",
          "site": {
            "id": 1,
            "name": "Château des Ducs de Bretagne"
          }
        }
      },
      {
        "item": {
          "id": 3,
          "name": "Statue de la Liberté",
          "site": {
            "id": 1,
            "name": "Château des Ducs de Bretagne"
          }
        }
      },
      {
        "item": {
          "id": 5,
          "name": "Manteau du Duc de Bretagne",
          "site": {
            "id": 1,
            "name": "Château des Ducs de Bretagne"
          }
        }
      }
    ]
  },
  {
    "id": 4,
    "name": "Exposition à Château d'Angers numéro 1",
    "shortDescription": "Exposition à Château d'Angers numéro 1",
    "longDescription": "Exposition à Château d'Angers description longue, en fait pas si longue mais suffisamment longue pour être considérée comme longue",
    "startDate": "1970-01-01T00:00:00.004Z",
    "endDate": "1970-06-15T00:00:00.004Z",
    "site": {
      "id": 2,
      "name": "Château d'Angers"
    },
    "exhibitedItems": [
      {
        "item": {
          "id": 9,
          "name": "Fresque de la chapelle",
          "site": {
            "id": 2,
            "name": "Château d'Angers"
          }
        }
      },
      {
        "item": {
          "id": 8,
          "name": "Sceptre de Charles d'Anjou",
          "site": {
            "id": 2,
            "name": "Château d'Angers"
          }
        }
      },
      {
        "item": {
          "id": 7,
          "name": "Coffre des trésors",
          "site": {
            "id": 2,
            "name": "Château d'Angers"
          }
        }
      }
    ]
  },
  {
    "id": 5,
    "name": "Exposition à Château d'Angers numéro 2",
    "shortDescription": "Exposition à Château d'Angers numéro 2",
    "longDescription": "Exposition à Château d'Angers description longue, en fait pas si longue mais suffisamment longue pour être considérée comme longue",
    "startDate": "1970-01-01T00:00:00.016Z",
    "endDate": "1970-05-31T00:00:00.016Z",
    "site": {
      "id": 2,
      "name": "Château d'Angers"
    },
    "exhibitedItems": [
      {
        "item": {
          "id": 6,
          "name": "Tapisserie de l'Apocalypse",
          "site": {
            "id": 2,
            "name": "Château d'Angers"
          }
        }
      },
      {
        "item": {
          "id": 10,
          "name": "Gant de velours",
          "site": {
            "id": 2,
            "name": "Château d'Angers"
          }
        }
      },
      {
        "item": {
          "id": 7,
          "name": "Coffre des trésors",
          "site": {
            "id": 2,
            "name": "Château d'Angers"
          }
        }
      }
    ]
  },
  {
    "id": 6,
    "name": "Exposition à Musée du Louvre numéro 1",
    "shortDescription": "Exposition à Musée du Louvre numéro 1",
    "longDescription": "Exposition à Musée du Louvre description longue, en fait pas si longue mais suffisamment longue pour être considérée comme longue",
    "startDate": "1970-01-01T00:00:00.032Z",
    "endDate": "1970-06-09T00:00:00.032Z",
    "site": {
      "id": 3,
      "name": "Musée du Louvre"
    },
    "exhibitedItems": [
      {
        "item": {
          "id": 11,
          "name": "Vase de l'antiquité",
          "site": {
            "id": 3,
            "name": "Musée du Louvre"
          }
        }
      },
      {
        "item": {
          "id": 12,
          "name": "Code de Hammurabi",
          "site": {
            "id": 3,
            "name": "Musée du Louvre"
          }
        }
      },
      {
        "item": {
          "id": 15,
          "name": "Peinture de David",
          "site": {
            "id": 3,
            "name": "Musée du Louvre"
          }
        }
      },
      {
        "item": {
          "id": 13,
          "name": "La Joconde",
          "site": {
            "id": 3,
            "name": "Musée du Louvre"
          }
        }
      },
      {
        "item": {
          "id": 14,
          "name": "Statue de la Liberté",
          "site": {
            "id": 3,
            "name": "Musée du Louvre"
          }
        }
      }
    ]
  },
  {
    "id": 7,
    "name": "Exposition à Musée du Louvre numéro 2",
    "shortDescription": "Exposition à Musée du Louvre numéro 2",
    "longDescription": "Exposition à Musée du Louvre description longue, en fait pas si longue mais suffisamment longue pour être considérée comme longue",
    "startDate": "1970-01-01T00:00:00.010Z",
    "endDate": "1970-06-13T00:00:00.010Z",
    "site": {
      "id": 3,
      "name": "Musée du Louvre"
    },
    "exhibitedItems": [
      {
        "item": {
          "id": 13,
          "name": "La Joconde",
          "site": {
            "id": 3,
            "name": "Musée du Louvre"
          }
        }
      },
      {
        "item": {
          "id": 12,
          "name": "Code de Hammurabi",
          "site": {
            "id": 3,
            "name": "Musée du Louvre"
          }
        }
      }
    ]
  },
  {
    "id": 8,
    "name": "Exposition à Musée du Louvre numéro 3",
    "shortDescription": "Exposition à Musée du Louvre numéro 3",
    "longDescription": "Exposition à Musée du Louvre description longue, en fait pas si longue mais suffisamment longue pour être considérée comme longue",
    "startDate": "1970-01-01T00:00:00.014Z",
    "endDate": "1970-02-11T00:00:00.014Z",
    "site": {
      "id": 3,
      "name": "Musée du Louvre"
    },
    "exhibitedItems": [
      {
        "item": {
          "id": 11,
          "name": "Vase de l'antiquité",
          "site": {
            "id": 3,
            "name": "Musée du Louvre"
          }
        }
      },
      {
        "item": {
          "id": 14,
          "name": "Statue de la Liberté",
          "site": {
            "id": 3,
            "name": "Musée du Louvre"
          }
        }
      }
    ]
  },
  {
    "id": 9,
    "name": "Exposition à Musée du Louvre numéro 4",
    "shortDescription": "Exposition à Musée du Louvre numéro 4",
    "longDescription": "Exposition à Musée du Louvre description longue, en fait pas si longue mais suffisamment longue pour être considérée comme longue",
    "startDate": "1970-01-01T00:00:00.012Z",
    "endDate": "1970-01-25T00:00:00.012Z",
    "site": {
      "id": 3,
      "name": "Musée du Louvre"
    },
    "exhibitedItems": [
      {
        "item": {
          "id": 11,
          "name": "Vase de l'antiquité",
          "site": {
            "id": 3,
            "name": "Musée du Louvre"
          }
        }
      }
    ]
  },
  {
    "id": 10,
    "name": "Exposition à Musée du Louvre numéro 5",
    "shortDescription": "Exposition à Musée du Louvre numéro 5",
    "longDescription": "Exposition à Musée du Louvre description longue, en fait pas si longue mais suffisamment longue pour être considérée comme longue",
    "startDate": "1970-01-01T00:00:00.026Z",
    "endDate": "1970-04-25T00:00:00.026Z",
    "site": {
      "id": 3,
      "name": "Musée du Louvre"
    },
    "exhibitedItems": [
      {
        "item": {
          "id": 11,
          "name": "Vase de l'antiquité",
          "site": {
            "id": 3,
            "name": "Musée du Louvre"
          }
        }
      },
      {
        "item": {
          "id": 14,
          "name": "Statue de la Liberté",
          "site": {
            "id": 3,
            "name": "Musée du Louvre"
          }
        }
      },
      {
        "item": {
          "id": 15,
          "name": "Peinture de David",
          "site": {
            "id": 3,
            "name": "Musée du Louvre"
          }
        }
      }
    ]
  },
  {
    "id": 11,
    "name": "Exposition à Centre Pompidou numéro 1",
    "shortDescription": "Exposition à Centre Pompidou numéro 1",
    "longDescription": "Exposition à Centre Pompidou description longue, en fait pas si longue mais suffisamment longue pour être considérée comme longue",
    "startDate": "1970-01-01T00:00:00.026Z",
    "endDate": "1970-04-09T00:00:00.026Z",
    "site": {
      "id": 4,
      "name": "Centre Pompidou"
    },
    "exhibitedItems": [
      {
        "item": {
          "id": 20,
          "name": "Fenêtre de Cézanne",
          "site": {
            "id": 4,
            "name": "Centre Pompidou"
          }
        }
      },
      {
        "item": {
          "id": 17,
          "name": "L'Homme qui marche",
          "site": {
            "id": 4,
            "name": "Centre Pompidou"
          }
        }
      },
      {
        "item": {
          "id": 16,
          "name": "Le Penseur",
          "site": {
            "id": 4,
            "name": "Centre Pompidou"
          }
        }
      },
      {
        "item": {
          "id": 18,
          "name": "Composition de Braque",
          "site": {
            "id": 4,
            "name": "Centre Pompidou"
          }
        }
      },
      {
        "item": {
          "id": 19,
          "name": "Le Sacre de Napoléon",
          "site": {
            "id": 4,
            "name": "Centre Pompidou"
          }
        }
      }
    ]
  },
  {
    "id": 12,
    "name": "Exposition à Palais Garnier numéro 1",
    "shortDescription": "Exposition à Palais Garnier numéro 1",
    "longDescription": "Exposition à Palais Garnier description longue, en fait pas si longue mais suffisamment longue pour être considérée comme longue",
    "startDate": "1970-01-01T00:00:00.010Z",
    "endDate": "1970-04-08T00:00:00.010Z",
    "site": {
      "id": 5,
      "name": "Palais Garnier"
    },
    "exhibitedItems": [
      {
        "item": {
          "id": 21,
          "name": "Costume de ballet",
          "site": {
            "id": 5,
            "name": "Palais Garnier"
          }
        }
      }
    ]
  },
  {
    "id": 13,
    "name": "Exposition à Palais Garnier numéro 2",
    "shortDescription": "Exposition à Palais Garnier numéro 2",
    "longDescription": "Exposition à Palais Garnier description longue, en fait pas si longue mais suffisamment longue pour être considérée comme longue",
    "startDate": "1970-01-01T00:00:00.009Z",
    "endDate": "1970-04-28T00:00:00.009Z",
    "site": {
      "id": 5,
      "name": "Palais Garnier"
    },
    "exhibitedItems": [
      {
        "item": {
          "id": 23,
          "name": "Maquette de l'Opéra",
          "site": {
            "id": 5,
            "name": "Palais Garnier"
          }
        }
      },
      {
        "item": {
          "id": 24,
          "name": "Affiche de ballet",
          "site": {
            "id": 5,
            "name": "Palais Garnier"
          }
        }
      },
      {
        "item": {
          "id": 22,
          "name": "Chandelier du Palais",
          "site": {
            "id": 5,
            "name": "Palais Garnier"
          }
        }
      }
    ]
  },
  {
    "id": 14,
    "name": "Exposition à Palais Garnier numéro 3",
    "shortDescription": "Exposition à Palais Garnier numéro 3",
    "longDescription": "Exposition à Palais Garnier description longue, en fait pas si longue mais suffisamment longue pour être considérée comme longue",
    "startDate": "1970-01-01T00:00:00.029Z",
    "endDate": "1970-05-30T00:00:00.029Z",
    "site": {
      "id": 5,
      "name": "Palais Garnier"
    },
    "exhibitedItems": [
      {
        "item": {
          "id": 23,
          "name": "Maquette de l'Opéra",
          "site": {
            "id": 5,
            "name": "Palais Garnier"
          }
        }
      },
      {
        "item": {
          "id": 21,
          "name": "Costume de ballet",
          "site": {
            "id": 5,
            "name": "Palais Garnier"
          }
        }
      },
      {
        "item": {
          "id": 24,
          "name": "Affiche de ballet",
          "site": {
            "id": 5,
            "name": "Palais Garnier"
          }
        }
      }
    ]
  },
  {
    "id": 15,
    "name": "Exposition à Musée des Beaux-Arts d'Angers numéro 1",
    "shortDescription": "Exposition à Musée des Beaux-Arts d'Angers numéro 1",
    "longDescription": "Exposition à Musée des Beaux-Arts d'Angers description longue, en fait pas si longue mais suffisamment longue pour être considérée comme longue",
    "startDate": "1970-01-01T00:00:00.031Z",
    "endDate": "1970-01-21T00:00:00.031Z",
    "site": {
      "id": 6,
      "name": "Musée des Beaux-Arts d'Angers"
    },
    "exhibitedItems": [
      {
        "item": {
          "id": 28,
          "name": "Vase antique",
          "site": {
            "id": 6,
            "name": "Musée des Beaux-Arts d'Angers"
          }
        }
      },
      {
        "item": {
          "id": 27,
          "name": "Portrait de Van Gogh",
          "site": {
            "id": 6,
            "name": "Musée des Beaux-Arts d'Angers"
          }
        }
      },
      {
        "item": {
          "id": 26,
          "name": "Sculpture de Rodin",
          "site": {
            "id": 6,
            "name": "Musée des Beaux-Arts d'Angers"
          }
        }
      }
    ]
  },
  {
    "id": 16,
    "name": "Exposition à Musée des Beaux-Arts d'Angers numéro 2",
    "shortDescription": "Exposition à Musée des Beaux-Arts d'Angers numéro 2",
    "longDescription": "Exposition à Musée des Beaux-Arts d'Angers description longue, en fait pas si longue mais suffisamment longue pour être considérée comme longue",
    "startDate": "1970-01-01T00:00:00.022Z",
    "endDate": "1970-06-01T00:00:00.022Z",
    "site": {
      "id": 6,
      "name": "Musée des Beaux-Arts d'Angers"
    },
    "exhibitedItems": [
      {
        "item": {
          "id": 27,
          "name": "Portrait de Van Gogh",
          "site": {
            "id": 6,
            "name": "Musée des Beaux-Arts d'Angers"
          }
        }
      },
      {
        "item": {
          "id": 26,
          "name": "Sculpture de Rodin",
          "site": {
            "id": 6,
            "name": "Musée des Beaux-Arts d'Angers"
          }
        }
      }
    ]
  },
  {
    "id": 17,
    "name": "Exposition à Musée des Beaux-Arts d'Angers numéro 3",
    "shortDescription": "Exposition à Musée des Beaux-Arts d'Angers numéro 3",
    "longDescription": "Exposition à Musée des Beaux-Arts d'Angers description longue, en fait pas si longue mais suffisamment longue pour être considérée comme longue",
    "startDate": "1970-01-01T00:00:00.002Z",
    "endDate": "1970-02-10T00:00:00.002Z",
    "site": {
      "id": 6,
      "name": "Musée des Beaux-Arts d'Angers"
    },
    "exhibitedItems": [
      {
        "item": {
          "id": 27,
          "name": "Portrait de Van Gogh",
          "site": {
            "id": 6,
            "name": "Musée des Beaux-Arts d'Angers"
          }
        }
      },
      {
        "item": {
          "id": 25,
          "name": "Peinture de Monet",
          "site": {
            "id": 6,
            "name": "Musée des Beaux-Arts d'Angers"
          }
        }
      },
      {
        "item": {
          "id": 26,
          "name": "Sculpture de Rodin",
          "site": {
            "id": 6,
            "name": "Musée des Beaux-Arts d'Angers"
          }
        }
      }
    ]
  },
  {
    "id": 18,
    "name": "Exposition à Musée des Beaux-Arts d'Angers numéro 4",
    "shortDescription": "Exposition à Musée des Beaux-Arts d'Angers numéro 4",
    "longDescription": "Exposition à Musée des Beaux-Arts d'Angers description longue, en fait pas si longue mais suffisamment longue pour être considérée comme longue",
    "startDate": "1970-01-01T00:00:00.011Z",
    "endDate": "1970-03-18T00:00:00.011Z",
    "site": {
      "id": 6,
      "name": "Musée des Beaux-Arts d'Angers"
    },
    "exhibitedItems": [
      {
        "item": {
          "id": 27,
          "name": "Portrait de Van Gogh",
          "site": {
            "id": 6,
            "name": "Musée des Beaux-Arts d'Angers"
          }
        }
      },
      {
        "item": {
          "id": 29,
          "name": "Mosaïque romaine",
          "site": {
            "id": 6,
            "name": "Musée des Beaux-Arts d'Angers"
          }
        }
      },
      {
        "item": {
          "id": 28,
          "name": "Vase antique",
          "site": {
            "id": 6,
            "name": "Musée des Beaux-Arts d'Angers"
          }
        }
      },
      {
        "item": {
          "id": 26,
          "name": "Sculpture de Rodin",
          "site": {
            "id": 6,
            "name": "Musée des Beaux-Arts d'Angers"
          }
        }
      }
    ]
  },
  {
    "id": 19,
    "name": "Exposition à Musée des Beaux-Arts d'Angers numéro 5",
    "shortDescription": "Exposition à Musée des Beaux-Arts d'Angers numéro 5",
    "longDescription": "Exposition à Musée des Beaux-Arts d'Angers description longue, en fait pas si longue mais suffisamment longue pour être considérée comme longue",
    "startDate": "1970-01-01T00:00:00.019Z",
    "endDate": "1970-04-09T00:00:00.019Z",
    "site": {
      "id": 6,
      "name": "Musée des Beaux-Arts d'Angers"
    },
    "exhibitedItems": [
      {
        "item": {
          "id": 28,
          "name": "Vase antique",
          "site": {
            "id": 6,
            "name": "Musée des Beaux-Arts d'Angers"
          }
        }
      },
      {
        "item": {
          "id": 29,
          "name": "Mosaïque romaine",
          "site": {
            "id": 6,
            "name": "Musée des Beaux-Arts d'Angers"
          }
        }
      },
      {
        "item": {
          "id": 27,
          "name": "Portrait de Van Gogh",
          "site": {
            "id": 6,
            "name": "Musée des Beaux-Arts d'Angers"
          }
        }
      },
      {
        "item": {
          "id": 25,
          "name": "Peinture de Monet",
          "site": {
            "id": 6,
            "name": "Musée des Beaux-Arts d'Angers"
          }
        }
      }
    ]
  },
  {
    "id": 20,
    "name": "Exposition à Musée de l'Histoire de la Médecine numéro 1",
    "shortDescription": "Exposition à Musée de l'Histoire de la Médecine numéro 1",
    "longDescription": "Exposition à Musée de l'Histoire de la Médecine description longue, en fait pas si longue mais suffisamment longue pour être considérée comme longue",
    "startDate": "1970-01-01T00:00:00.010Z",
    "endDate": "1970-02-01T00:00:00.010Z",
    "site": {
      "id": 7,
      "name": "Musée de l'Histoire de la Médecine"
    },
    "exhibitedItems": [
      {
        "item": {
          "id": 33,
          "name": "Instruments de saignées",
          "site": {
            "id": 7,
            "name": "Musée de l'Histoire de la Médecine"
          }
        }
      }
    ]
  },
  {
    "id": 21,
    "name": "Exposition à Musée de l'Histoire de la Médecine numéro 2",
    "shortDescription": "Exposition à Musée de l'Histoire de la Médecine numéro 2",
    "longDescription": "Exposition à Musée de l'Histoire de la Médecine description longue, en fait pas si longue mais suffisamment longue pour être considérée comme longue",
    "startDate": "1970-01-01T00:00:00.002Z",
    "endDate": "1970-02-17T00:00:00.002Z",
    "site": {
      "id": 7,
      "name": "Musée de l'Histoire de la Médecine"
    },
    "exhibitedItems": [
      {
        "item": {
          "id": 33,
          "name": "Instruments de saignées",
          "site": {
            "id": 7,
            "name": "Musée de l'Histoire de la Médecine"
          }
        }
      },
      {
        "item": {
          "id": 32,
          "name": "Manuel de chirurgie",
          "site": {
            "id": 7,
            "name": "Musée de l'Histoire de la Médecine"
          }
        }
      }
    ]
  },
  {
    "id": 22,
    "name": "Exposition à Musée de l'Histoire de la Médecine numéro 3",
    "shortDescription": "Exposition à Musée de l'Histoire de la Médecine numéro 3",
    "longDescription": "Exposition à Musée de l'Histoire de la Médecine description longue, en fait pas si longue mais suffisamment longue pour être considérée comme longue",
    "startDate": "1970-01-01T00:00:00.018Z",
    "endDate": "1970-06-03T00:00:00.018Z",
    "site": {
      "id": 7,
      "name": "Musée de l'Histoire de la Médecine"
    },
    "exhibitedItems": [
      {
        "item": {
          "id": 31,
          "name": "Appareil de désarticulation",
          "site": {
            "id": 7,
            "name": "Musée de l'Histoire de la Médecine"
          }
        }
      },
      {
        "item": {
          "id": 30,
          "name": "Squelette humain",
          "site": {
            "id": 7,
            "name": "Musée de l'Histoire de la Médecine"
          }
        }
      },
      {
        "item": {
          "id": 33,
          "name": "Instruments de saignées",
          "site": {
            "id": 7,
            "name": "Musée de l'Histoire de la Médecine"
          }
        }
      }
    ]
  },
  {
    "id": 23,
    "name": "Exposition à Musée d'Arts de Nantes numéro 1",
    "shortDescription": "Exposition à Musée d'Arts de Nantes numéro 1",
    "longDescription": "Exposition à Musée d'Arts de Nantes description longue, en fait pas si longue mais suffisamment longue pour être considérée comme longue",
    "startDate": "1970-01-01T00:00:00.004Z",
    "endDate": "1970-05-31T00:00:00.004Z",
    "site": {
      "id": 8,
      "name": "Musée d'Arts de Nantes"
    },
    "exhibitedItems": [
      {
        "item": {
          "id": 38,
          "name": "Installation interactive",
          "site": {
            "id": 8,
            "name": "Musée d'Arts de Nantes"
          }
        }
      },
      {
        "item": {
          "id": 36,
          "name": "Sculpture de marbre",
          "site": {
            "id": 8,
            "name": "Musée d'Arts de Nantes"
          }
        }
      },
      {
        "item": {
          "id": 39,
          "name": "Tapisserie médiévale",
          "site": {
            "id": 8,
            "name": "Musée d'Arts de Nantes"
          }
        }
      }
    ]
  },
  {
    "id": 24,
    "name": "Exposition à Musée d'Arts de Nantes numéro 2",
    "shortDescription": "Exposition à Musée d'Arts de Nantes numéro 2",
    "longDescription": "Exposition à Musée d'Arts de Nantes description longue, en fait pas si longue mais suffisamment longue pour être considérée comme longue",
    "startDate": "1970-01-01T00:00:00.032Z",
    "endDate": "1970-05-23T00:00:00.032Z",
    "site": {
      "id": 8,
      "name": "Musée d'Arts de Nantes"
    },
    "exhibitedItems": [
      {
        "item": {
          "id": 37,
          "name": "Tableau abstrait",
          "site": {
            "id": 8,
            "name": "Musée d'Arts de Nantes"
          }
        }
      },
      {
        "item": {
          "id": 39,
          "name": "Tapisserie médiévale",
          "site": {
            "id": 8,
            "name": "Musée d'Arts de Nantes"
          }
        }
      },
      {
        "item": {
          "id": 35,
          "name": "Portrait de femme",
          "site": {
            "id": 8,
            "name": "Musée d'Arts de Nantes"
          }
        }
      },
      {
        "item": {
          "id": 36,
          "name": "Sculpture de marbre",
          "site": {
            "id": 8,
            "name": "Musée d'Arts de Nantes"
          }
        }
      },
      {
        "item": {
          "id": 38,
          "name": "Installation interactive",
          "site": {
            "id": 8,
            "name": "Musée d'Arts de Nantes"
          }
        }
      }
    ]
  },
  {
    "id": 25,
    "name": "Exposition à Musée d'Arts de Nantes numéro 3",
    "shortDescription": "Exposition à Musée d'Arts de Nantes numéro 3",
    "longDescription": "Exposition à Musée d'Arts de Nantes description longue, en fait pas si longue mais suffisamment longue pour être considérée comme longue",
    "startDate": "1970-01-01T00:00:00.024Z",
    "endDate": "1970-04-07T00:00:00.024Z",
    "site": {
      "id": 8,
      "name": "Musée d'Arts de Nantes"
    },
    "exhibitedItems": [
      {
        "item": {
          "id": 39,
          "name": "Tapisserie médiévale",
          "site": {
            "id": 8,
            "name": "Musée d'Arts de Nantes"
          }
        }
      },
      {
        "item": {
          "id": 37,
          "name": "Tableau abstrait",
          "site": {
            "id": 8,
            "name": "Musée d'Arts de Nantes"
          }
        }
      }
    ]
  },
  {
    "id": 26,
    "name": "Exposition à Musée d'Arts de Nantes numéro 4",
    "shortDescription": "Exposition à Musée d'Arts de Nantes numéro 4",
    "longDescription": "Exposition à Musée d'Arts de Nantes description longue, en fait pas si longue mais suffisamment longue pour être considérée comme longue",
    "startDate": "1970-01-01T00:00:00.008Z",
    "endDate": "1970-06-30T00:00:00.008Z",
    "site": {
      "id": 8,
      "name": "Musée d'Arts de Nantes"
    },
    "exhibitedItems": [
      {
        "item": {
          "id": 36,
          "name": "Sculpture de marbre",
          "site": {
            "id": 8,
            "name": "Musée d'Arts de Nantes"
          }
        }
      },
      {
        "item": {
          "id": 35,
          "name": "Portrait de femme",
          "site": {
            "id": 8,
            "name": "Musée d'Arts de Nantes"
          }
        }
      },
      {
        "item": {
          "id": 38,
          "name": "Installation interactive",
          "site": {
            "id": 8,
            "name": "Musée d'Arts de Nantes"
          }
        }
      },
      {
        "item": {
          "id": 37,
          "name": "Tableau abstrait",
          "site": {
            "id": 8,
            "name": "Musée d'Arts de Nantes"
          }
        }
      },
      {
        "item": {
          "id": 39,
          "name": "Tapisserie médiévale",
          "site": {
            "id": 8,
            "name": "Musée d'Arts de Nantes"
          }
        }
      }
    ]
  },
  {
    "id": 27,
    "name": "Exposition à Musée de l'Orangerie numéro 1",
    "shortDescription": "Exposition à Musée de l'Orangerie numéro 1",
    "longDescription": "Exposition à Musée de l'Orangerie description longue, en fait pas si longue mais suffisamment longue pour être considérée comme longue",
    "startDate": "1970-01-01T00:00:00.031Z",
    "endDate": "1970-05-23T00:00:00.031Z",
    "site": {
      "id": 9,
      "name": "Musée de l'Orangerie"
    },
    "exhibitedItems": [
      {
        "item": {
          "id": 43,
          "name": "Nature morte",
          "site": {
            "id": 9,
            "name": "Musée de l'Orangerie"
          }
        }
      }
    ]
  },
  {
    "id": 28,
    "name": "Exposition à Musée de l'Orangerie numéro 2",
    "shortDescription": "Exposition à Musée de l'Orangerie numéro 2",
    "longDescription": "Exposition à Musée de l'Orangerie description longue, en fait pas si longue mais suffisamment longue pour être considérée comme longue",
    "startDate": "1970-01-01T00:00:00.024Z",
    "endDate": "1970-02-27T00:00:00.024Z",
    "site": {
      "id": 9,
      "name": "Musée de l'Orangerie"
    },
    "exhibitedItems": [
      {
        "item": {
          "id": 40,
          "name": "Nymphéas",
          "site": {
            "id": 9,
            "name": "Musée de l'Orangerie"
          }
        }
      },
      {
        "item": {
          "id": 41,
          "name": "Sculpture de Camille Claudel",
          "site": {
            "id": 9,
            "name": "Musée de l'Orangerie"
          }
        }
      },
      {
        "item": {
          "id": 43,
          "name": "Nature morte",
          "site": {
            "id": 9,
            "name": "Musée de l'Orangerie"
          }
        }
      }
    ]
  },
  {
    "id": 29,
    "name": "Exposition à Palais Royal numéro 1",
    "shortDescription": "Exposition à Palais Royal numéro 1",
    "longDescription": "Exposition à Palais Royal description longue, en fait pas si longue mais suffisamment longue pour être considérée comme longue",
    "startDate": "1970-01-01T00:00:00.028Z",
    "endDate": "1970-02-13T00:00:00.028Z",
    "site": {
      "id": 10,
      "name": "Palais Royal"
    },
    "exhibitedItems": [
      {
        "item": {
          "id": 45,
          "name": "Fontaine du Palais Royal",
          "site": {
            "id": 10,
            "name": "Palais Royal"
          }
        }
      }
    ]
  },
  {
    "id": 30,
    "name": "Exposition à Palais Royal numéro 2",
    "shortDescription": "Exposition à Palais Royal numéro 2",
    "longDescription": "Exposition à Palais Royal description longue, en fait pas si longue mais suffisamment longue pour être considérée comme longue",
    "startDate": "1970-01-01T00:00:00.014Z",
    "endDate": "1970-06-23T00:00:00.014Z",
    "site": {
      "id": 10,
      "name": "Palais Royal"
    },
    "exhibitedItems": [
      {
        "item": {
          "id": 44,
          "name": "Jardin du Palais",
          "site": {
            "id": 10,
            "name": "Palais Royal"
          }
        }
      }
    ]
  },
  {
    "id": 31,
    "name": "Exposition à Musée de l'Armée numéro 1",
    "shortDescription": "Exposition à Musée de l'Armée numéro 1",
    "longDescription": "Exposition à Musée de l'Armée description longue, en fait pas si longue mais suffisamment longue pour être considérée comme longue",
    "startDate": "1970-01-01T00:00:00.024Z",
    "endDate": "1970-04-24T00:00:00.024Z",
    "site": {
      "id": 11,
      "name": "Musée de l'Armée"
    },
    "exhibitedItems": [
      {
        "item": {
          "id": 46,
          "name": "Armure médiévale",
          "site": {
            "id": 11,
            "name": "Musée de l'Armée"
          }
        }
      }
    ]
  },
  {
    "id": 32,
    "name": "Exposition à Musée du quai Branly numéro 1",
    "shortDescription": "Exposition à Musée du quai Branly numéro 1",
    "longDescription": "Exposition à Musée du quai Branly description longue, en fait pas si longue mais suffisamment longue pour être considérée comme longue",
    "startDate": "1970-01-01T00:00:00.025Z",
    "endDate": "1970-06-26T00:00:00.025Z",
    "site": {
      "id": 12,
      "name": "Musée du quai Branly"
    },
    "exhibitedItems": [
      {
        "item": {
          "id": 51,
          "name": "Masque tribal",
          "site": {
            "id": 12,
            "name": "Musée du quai Branly"
          }
        }
      },
      {
        "item": {
          "id": 52,
          "name": "Statue d'ancêtre",
          "site": {
            "id": 12,
            "name": "Musée du quai Branly"
          }
        }
      },
      {
        "item": {
          "id": 55,
          "name": "Parure en perles",
          "site": {
            "id": 12,
            "name": "Musée du quai Branly"
          }
        }
      },
      {
        "item": {
          "id": 53,
          "name": "Tissu traditionnel",
          "site": {
            "id": 12,
            "name": "Musée du quai Branly"
          }
        }
      }
    ]
  },
  {
    "id": 33,
    "name": "Exposition à Musée du quai Branly numéro 2",
    "shortDescription": "Exposition à Musée du quai Branly numéro 2",
    "longDescription": "Exposition à Musée du quai Branly description longue, en fait pas si longue mais suffisamment longue pour être considérée comme longue",
    "startDate": "1970-01-01T00:00:00.027Z",
    "endDate": "1970-03-24T00:00:00.027Z",
    "site": {
      "id": 12,
      "name": "Musée du quai Branly"
    },
    "exhibitedItems": [
      {
        "item": {
          "id": 54,
          "name": "Instrument de musique",
          "site": {
            "id": 12,
            "name": "Musée du quai Branly"
          }
        }
      },
      {
        "item": {
          "id": 51,
          "name": "Masque tribal",
          "site": {
            "id": 12,
            "name": "Musée du quai Branly"
          }
        }
      },
      {
        "item": {
          "id": 53,
          "name": "Tissu traditionnel",
          "site": {
            "id": 12,
            "name": "Musée du quai Branly"
          }
        }
      },
      {
        "item": {
          "id": 52,
          "name": "Statue d'ancêtre",
          "site": {
            "id": 12,
            "name": "Musée du quai Branly"
          }
        }
      },
      {
        "item": {
          "id": 55,
          "name": "Parure en perles",
          "site": {
            "id": 12,
            "name": "Musée du quai Branly"
          }
        }
      }
    ]
  },
  {
    "id": 34,
    "name": "Exposition à Musée du quai Branly numéro 3",
    "shortDescription": "Exposition à Musée du quai Branly numéro 3",
    "longDescription": "Exposition à Musée du quai Branly description longue, en fait pas si longue mais suffisamment longue pour être considérée comme longue",
    "startDate": "1970-01-01T00:00:00.025Z",
    "endDate": "1970-04-01T00:00:00.025Z",
    "site": {
      "id": 12,
      "name": "Musée du quai Branly"
    },
    "exhibitedItems": [
      {
        "item": {
          "id": 54,
          "name": "Instrument de musique",
          "site": {
            "id": 12,
            "name": "Musée du quai Branly"
          }
        }
      }
    ]
  },
  {
    "id": 35,
    "name": "Exposition à Musée du quai Branly numéro 4",
    "shortDescription": "Exposition à Musée du quai Branly numéro 4",
    "longDescription": "Exposition à Musée du quai Branly description longue, en fait pas si longue mais suffisamment longue pour être considérée comme longue",
    "startDate": "1970-01-01T00:00:00.002Z",
    "endDate": "1970-02-04T00:00:00.002Z",
    "site": {
      "id": 12,
      "name": "Musée du quai Branly"
    },
    "exhibitedItems": [
      {
        "item": {
          "id": 54,
          "name": "Instrument de musique",
          "site": {
            "id": 12,
            "name": "Musée du quai Branly"
          }
        }
      }
    ]
  },
  {
    "id": 36,
    "name": "Exposition à Musée du quai Branly numéro 5",
    "shortDescription": "Exposition à Musée du quai Branly numéro 5",
    "longDescription": "Exposition à Musée du quai Branly description longue, en fait pas si longue mais suffisamment longue pour être considérée comme longue",
    "startDate": "1970-01-01T00:00:00.005Z",
    "endDate": "1970-02-10T00:00:00.005Z",
    "site": {
      "id": 12,
      "name": "Musée du quai Branly"
    },
    "exhibitedItems": [
      {
        "item": {
          "id": 54,
          "name": "Instrument de musique",
          "site": {
            "id": 12,
            "name": "Musée du quai Branly"
          }
        }
      }
    ]
  },
  {
    "id": 37,
    "name": "Exposition à Musée des Arts Décoratifs numéro 1",
    "shortDescription": "Exposition à Musée des Arts Décoratifs numéro 1",
    "longDescription": "Exposition à Musée des Arts Décoratifs description longue, en fait pas si longue mais suffisamment longue pour être considérée comme longue",
    "startDate": "1970-01-01T00:00:00.011Z",
    "endDate": "1970-06-07T00:00:00.011Z",
    "site": {
      "id": 13,
      "name": "Musée des Arts Décoratifs"
    },
    "exhibitedItems": [
      {
        "item": {
          "id": 58,
          "name": "Tapis persan",
          "site": {
            "id": 13,
            "name": "Musée des Arts Décoratifs"
          }
        }
      },
      {
        "item": {
          "id": 59,
          "name": "Porcelaine de Sèvres",
          "site": {
            "id": 13,
            "name": "Musée des Arts Décoratifs"
          }
        }
      },
      {
        "item": {
          "id": 57,
          "name": "Chaise en bois",
          "site": {
            "id": 13,
            "name": "Musée des Arts Décoratifs"
          }
        }
      },
      {
        "item": {
          "id": 56,
          "name": "Vase Art Déco",
          "site": {
            "id": 13,
            "name": "Musée des Arts Décoratifs"
          }
        }
      },
      {
        "item": {
          "id": 60,
          "name": "Lampe Art Nouveau",
          "site": {
            "id": 13,
            "name": "Musée des Arts Décoratifs"
          }
        }
      }
    ]
  },
  {
    "id": 38,
    "name": "Exposition à Institut Lumière numéro 1",
    "shortDescription": "Exposition à Institut Lumière numéro 1",
    "longDescription": "Exposition à Institut Lumière description longue, en fait pas si longue mais suffisamment longue pour être considérée comme longue",
    "startDate": "1970-01-01T00:00:00.008Z",
    "endDate": "1970-01-20T00:00:00.008Z",
    "site": {
      "id": 14,
      "name": "Institut Lumière"
    },
    "exhibitedItems": [
      {
        "item": {
          "id": 62,
          "name": "Affiche de film",
          "site": {
            "id": 14,
            "name": "Institut Lumière"
          }
        }
      }
    ]
  },
  {
    "id": 39,
    "name": "Exposition à Institut Lumière numéro 2",
    "shortDescription": "Exposition à Institut Lumière numéro 2",
    "longDescription": "Exposition à Institut Lumière description longue, en fait pas si longue mais suffisamment longue pour être considérée comme longue",
    "startDate": "1970-01-01T00:00:00.021Z",
    "endDate": "1970-03-19T00:00:00.021Z",
    "site": {
      "id": 14,
      "name": "Institut Lumière"
    },
    "exhibitedItems": [
      {
        "item": {
          "id": 62,
          "name": "Affiche de film",
          "site": {
            "id": 14,
            "name": "Institut Lumière"
          }
        }
      },
      {
        "item": {
          "id": 64,
          "name": "Scénario original",
          "site": {
            "id": 14,
            "name": "Institut Lumière"
          }
        }
      }
    ]
  },
  {
    "id": 40,
    "name": "Exposition à Institut Lumière numéro 3",
    "shortDescription": "Exposition à Institut Lumière numéro 3",
    "longDescription": "Exposition à Institut Lumière description longue, en fait pas si longue mais suffisamment longue pour être considérée comme longue",
    "startDate": "1970-01-01T00:00:00.020Z",
    "endDate": "1970-05-28T00:00:00.020Z",
    "site": {
      "id": 14,
      "name": "Institut Lumière"
    },
    "exhibitedItems": [
      {
        "item": {
          "id": 64,
          "name": "Scénario original",
          "site": {
            "id": 14,
            "name": "Institut Lumière"
          }
        }
      }
    ]
  },
  {
    "id": 41,
    "name": "Exposition à Institut Lumière numéro 4",
    "shortDescription": "Exposition à Institut Lumière numéro 4",
    "longDescription": "Exposition à Institut Lumière description longue, en fait pas si longue mais suffisamment longue pour être considérée comme longue",
    "startDate": "1970-01-01T00:00:00.029Z",
    "endDate": "1970-04-26T00:00:00.029Z",
    "site": {
      "id": 14,
      "name": "Institut Lumière"
    },
    "exhibitedItems": [
      {
        "item": {
          "id": 61,
          "name": "Caméra de projection",
          "site": {
            "id": 14,
            "name": "Institut Lumière"
          }
        }
      },
      {
        "item": {
          "id": 62,
          "name": "Affiche de film",
          "site": {
            "id": 14,
            "name": "Institut Lumière"
          }
        }
      },
      {
        "item": {
          "id": 63,
          "name": "Projecteur de films",
          "site": {
            "id": 14,
            "name": "Institut Lumière"
          }
        }
      },
      {
        "item": {
          "id": 64,
          "name": "Scénario original",
          "site": {
            "id": 14,
            "name": "Institut Lumière"
          }
        }
      }
    ]
  },
  {
    "id": 42,
    "name": "Exposition à Institut Lumière numéro 5",
    "shortDescription": "Exposition à Institut Lumière numéro 5",
    "longDescription": "Exposition à Institut Lumière description longue, en fait pas si longue mais suffisamment longue pour être considérée comme longue",
    "startDate": "1970-01-01T00:00:00.027Z",
    "endDate": "1970-05-14T00:00:00.027Z",
    "site": {
      "id": 14,
      "name": "Institut Lumière"
    },
    "exhibitedItems": [
      {
        "item": {
          "id": 64,
          "name": "Scénario original",
          "site": {
            "id": 14,
            "name": "Institut Lumière"
          }
        }
      },
      {
        "item": {
          "id": 63,
          "name": "Projecteur de films",
          "site": {
            "id": 14,
            "name": "Institut Lumière"
          }
        }
      },
      {
        "item": {
          "id": 62,
          "name": "Affiche de film",
          "site": {
            "id": 14,
            "name": "Institut Lumière"
          }
        }
      }
    ]
  },
  {
    "id": 43,
    "name": "Exposition à Musée des Confluences numéro 1",
    "shortDescription": "Exposition à Musée des Confluences numéro 1",
    "longDescription": "Exposition à Musée des Confluences description longue, en fait pas si longue mais suffisamment longue pour être considérée comme longue",
    "startDate": "1970-01-01T00:00:00.015Z",
    "endDate": "1970-04-20T00:00:00.015Z",
    "site": {
      "id": 15,
      "name": "Musée des Confluences"
    },
    "exhibitedItems": [
      {
        "item": {
          "id": 67,
          "name": "Outils préhistoriques",
          "site": {
            "id": 15,
            "name": "Musée des Confluences"
          }
        }
      },
      {
        "item": {
          "id": 66,
          "name": "Masque africain",
          "site": {
            "id": 15,
            "name": "Musée des Confluences"
          }
        }
      },
      {
        "item": {
          "id": 65,
          "name": "Squelette de dinosaure",
          "site": {
            "id": 15,
            "name": "Musée des Confluences"
          }
        }
      },
      {
        "item": {
          "id": 69,
          "name": "Poupée en terre cuite",
          "site": {
            "id": 15,
            "name": "Musée des Confluences"
          }
        }
      },
      {
        "item": {
          "id": 68,
          "name": "Parure de bijoux anciens",
          "site": {
            "id": 15,
            "name": "Musée des Confluences"
          }
        }
      }
    ]
  },
  {
    "id": 44,
    "name": "Exposition à Musée des Confluences numéro 2",
    "shortDescription": "Exposition à Musée des Confluences numéro 2",
    "longDescription": "Exposition à Musée des Confluences description longue, en fait pas si longue mais suffisamment longue pour être considérée comme longue",
    "startDate": "1970-01-01T00:00:00.021Z",
    "endDate": "1970-02-22T00:00:00.021Z",
    "site": {
      "id": 15,
      "name": "Musée des Confluences"
    },
    "exhibitedItems": [
      {
        "item": {
          "id": 69,
          "name": "Poupée en terre cuite",
          "site": {
            "id": 15,
            "name": "Musée des Confluences"
          }
        }
      }
    ]
  },
  {
    "id": 45,
    "name": "Exposition à Musée des Confluences numéro 3",
    "shortDescription": "Exposition à Musée des Confluences numéro 3",
    "longDescription": "Exposition à Musée des Confluences description longue, en fait pas si longue mais suffisamment longue pour être considérée comme longue",
    "startDate": "1970-01-01T00:00:00.023Z",
    "endDate": "1970-06-09T00:00:00.023Z",
    "site": {
      "id": 15,
      "name": "Musée des Confluences"
    },
    "exhibitedItems": [
      {
        "item": {
          "id": 65,
          "name": "Squelette de dinosaure",
          "site": {
            "id": 15,
            "name": "Musée des Confluences"
          }
        }
      }
    ]
  },
  {
    "id": 46,
    "name": "Exposition à Musée des Confluences numéro 4",
    "shortDescription": "Exposition à Musée des Confluences numéro 4",
    "longDescription": "Exposition à Musée des Confluences description longue, en fait pas si longue mais suffisamment longue pour être considérée comme longue",
    "startDate": "1970-01-01T00:00:00.010Z",
    "endDate": "1970-02-12T00:00:00.010Z",
    "site": {
      "id": 15,
      "name": "Musée des Confluences"
    },
    "exhibitedItems": [
      {
        "item": {
          "id": 66,
          "name": "Masque africain",
          "site": {
            "id": 15,
            "name": "Musée des Confluences"
          }
        }
      },
      {
        "item": {
          "id": 65,
          "name": "Squelette de dinosaure",
          "site": {
            "id": 15,
            "name": "Musée des Confluences"
          }
        }
      },
      {
        "item": {
          "id": 68,
          "name": "Parure de bijoux anciens",
          "site": {
            "id": 15,
            "name": "Musée des Confluences"
          }
        }
      }
    ]
  },
  {
    "id": 47,
    "name": "Exposition à Musée des Confluences numéro 5",
    "shortDescription": "Exposition à Musée des Confluences numéro 5",
    "longDescription": "Exposition à Musée des Confluences description longue, en fait pas si longue mais suffisamment longue pour être considérée comme longue",
    "startDate": "1970-01-01T00:00:00.013Z",
    "endDate": "1970-03-05T00:00:00.013Z",
    "site": {
      "id": 15,
      "name": "Musée des Confluences"
    },
    "exhibitedItems": [
      {
        "item": {
          "id": 67,
          "name": "Outils préhistoriques",
          "site": {
            "id": 15,
            "name": "Musée des Confluences"
          }
        }
      },
      {
        "item": {
          "id": 66,
          "name": "Masque africain",
          "site": {
            "id": 15,
            "name": "Musée des Confluences"
          }
        }
      },
      {
        "item": {
          "id": 65,
          "name": "Squelette de dinosaure",
          "site": {
            "id": 15,
            "name": "Musée des Confluences"
          }
        }
      },
      {
        "item": {
          "id": 68,
          "name": "Parure de bijoux anciens",
          "site": {
            "id": 15,
            "name": "Musée des Confluences"
          }
        }
      },
      {
        "item": {
          "id": 69,
          "name": "Poupée en terre cuite",
          "site": {
            "id": 15,
            "name": "Musée des Confluences"
          }
        }
      }
    ]
  },
  {
    "id": 48,
    "name": "Exposition à Musée de la Préfecture de Police numéro 1",
    "shortDescription": "Exposition à Musée de la Préfecture de Police numéro 1",
    "longDescription": "Exposition à Musée de la Préfecture de Police description longue, en fait pas si longue mais suffisamment longue pour être considérée comme longue",
    "startDate": "1970-01-01T00:00:00.006Z",
    "endDate": "1970-03-24T00:00:00.006Z",
    "site": {
      "id": 16,
      "name": "Musée de la Préfecture de Police"
    },
    "exhibitedItems": [
      {
        "item": {
          "id": 73,
          "name": "Plan de la ville",
          "site": {
            "id": 16,
            "name": "Musée de la Préfecture de Police"
          }
        }
      }
    ]
  },
  {
    "id": 49,
    "name": "Exposition à Musée de la Préfecture de Police numéro 2",
    "shortDescription": "Exposition à Musée de la Préfecture de Police numéro 2",
    "longDescription": "Exposition à Musée de la Préfecture de Police description longue, en fait pas si longue mais suffisamment longue pour être considérée comme longue",
    "startDate": "1970-01-01T00:00:00.025Z",
    "endDate": "1970-02-14T00:00:00.025Z",
    "site": {
      "id": 16,
      "name": "Musée de la Préfecture de Police"
    },
    "exhibitedItems": [
      {
        "item": {
          "id": 73,
          "name": "Plan de la ville",
          "site": {
            "id": 16,
            "name": "Musée de la Préfecture de Police"
          }
        }
      }
    ]
  },
  {
    "id": 50,
    "name": "Exposition à Musée de la Préfecture de Police numéro 3",
    "shortDescription": "Exposition à Musée de la Préfecture de Police numéro 3",
    "longDescription": "Exposition à Musée de la Préfecture de Police description longue, en fait pas si longue mais suffisamment longue pour être considérée comme longue",
    "startDate": "1970-01-01T00:00:00.015Z",
    "endDate": "1970-03-29T00:00:00.015Z",
    "site": {
      "id": 16,
      "name": "Musée de la Préfecture de Police"
    },
    "exhibitedItems": [
      {
        "item": {
          "id": 70,
          "name": "Uniforme de police",
          "site": {
            "id": 16,
            "name": "Musée de la Préfecture de Police"
          }
        }
      }
    ]
  },
  {
    "id": 51,
    "name": "Exposition à Musée de la Préfecture de Police numéro 4",
    "shortDescription": "Exposition à Musée de la Préfecture de Police numéro 4",
    "longDescription": "Exposition à Musée de la Préfecture de Police description longue, en fait pas si longue mais suffisamment longue pour être considérée comme longue",
    "startDate": "1970-01-01T00:00:00.030Z",
    "endDate": "1970-02-22T00:00:00.030Z",
    "site": {
      "id": 16,
      "name": "Musée de la Préfecture de Police"
    },
    "exhibitedItems": [
      {
        "item": {
          "id": 72,
          "name": "Dossier d'enquête",
          "site": {
            "id": 16,
            "name": "Musée de la Préfecture de Police"
          }
        }
      },
      {
        "item": {
          "id": 74,
          "name": "Appareil photo ancien",
          "site": {
            "id": 16,
            "name": "Musée de la Préfecture de Police"
          }
        }
      },
      {
        "item": {
          "id": 70,
          "name": "Uniforme de police",
          "site": {
            "id": 16,
            "name": "Musée de la Préfecture de Police"
          }
        }
      },
      {
        "item": {
          "id": 71,
          "name": "Révolver",
          "site": {
            "id": 16,
            "name": "Musée de la Préfecture de Police"
          }
        }
      }
    ]
  },
  {
    "id": 52,
    "name": "Exposition à Musée de la Préfecture de Police numéro 5",
    "shortDescription": "Exposition à Musée de la Préfecture de Police numéro 5",
    "longDescription": "Exposition à Musée de la Préfecture de Police description longue, en fait pas si longue mais suffisamment longue pour être considérée comme longue",
    "startDate": "1970-01-01T00:00:00.023Z",
    "endDate": "1970-06-27T00:00:00.023Z",
    "site": {
      "id": 16,
      "name": "Musée de la Préfecture de Police"
    },
    "exhibitedItems": [
      {
        "item": {
          "id": 72,
          "name": "Dossier d'enquête",
          "site": {
            "id": 16,
            "name": "Musée de la Préfecture de Police"
          }
        }
      },
      {
        "item": {
          "id": 74,
          "name": "Appareil photo ancien",
          "site": {
            "id": 16,
            "name": "Musée de la Préfecture de Police"
          }
        }
      },
      {
        "item": {
          "id": 70,
          "name": "Uniforme de police",
          "site": {
            "id": 16,
            "name": "Musée de la Préfecture de Police"
          }
        }
      }
    ]
  }
]